gapa/__init__.py
gapa/DeepLearning/ChebNet.py
gapa/DeepLearning/Classifier.py
gapa/DeepLearning/GCN.py
gapa/DeepLearning/SGC.py
gapa/DeepLearning/__init__.py
gapa/DeepLearning/config.py
gapa/DeepLearning/utils.py
gapa/algorithm/__init__.py
gapa/algorithm/CDA/CGN.py
gapa/algorithm/CDA/EDA.py
gapa/algorithm/CDA/Genes.py
gapa/algorithm/CDA/QAttack.py
gapa/algorithm/CDA/__init__.py
gapa/algorithm/CND/Cutoff.py
gapa/algorithm/CND/SixDST.py
gapa/algorithm/CND/TDE.py
gapa/algorithm/CND/__init__.py
gapa/algorithm/LPA/EDA.py
gapa/algorithm/LPA/LPA_GA.py
gapa/algorithm/LPA/__init__.py
gapa/algorithm/NCA/NCA_GA.py
gapa/algorithm/NCA/SGA.py
gapa/algorithm/NCA/__init__.py
gapa/framework/__init__.py
gapa/framework/body.py
gapa/framework/controller.py
gapa/framework/evaluator.py
gapa/utils/DataLoader.py
gapa/utils/__init__.py
gapa/utils/dataset.py
gapa/utils/functions.py
gapa/utils/init_device.py
gapa-0.0.2.dist-info/LICENSE
gapa-0.0.2.dist-info/METADATA
gapa-0.0.2.dist-info/WHEEL
gapa-0.0.2.dist-info/top_level.txt
gapa-0.0.2.dist-info/RECORD
