Metadata-Version: 2.1
Name: gapa
Version: 0.0.2
Summary: A PyTorch library for accelerating Genetic Algorithm in Perturbed SubStructure Optimization.
Home-page: https://github.com/NetAlsGroup/GAPA
Author: netalsgroup
Author-email: netalsgroup@gmail.com
License: MIT
Project-URL: Homepage, https://github.com/NetAlsGroup/GAPA
Project-URL: Issues, https://github.com/NetAlsGroup/GAPA/issues
Classifier: Development Status :: 3 - Alpha
Classifier: Programming Language :: Python :: 3
Classifier: License :: OSI Approved :: MIT License
Classifier: Intended Audience :: Developers
Classifier: Intended Audience :: Education
Classifier: Intended Audience :: Science/Research
Classifier: Topic :: Scientific/Engineering :: Mathematics
Classifier: Operating System :: OS Independent
Requires-Python: >=3.9
License-File: LICENSE
Requires-Dist: numpy (>=1.26.3)
Requires-Dist: pandas (>=2.2.1)
Requires-Dist: matplotlib (>=3.8.4)
Requires-Dist: scipy (>=1.10.1)
Requires-Dist: networkx (>=3.2.1)
Requires-Dist: igraph (>=0.11.5)
Requires-Dist: tqdm (>=4.48.2)
Requires-Dist: yacs (>=0.1.8)
Provides-Extra: cpu
Requires-Dist: torch (>=2.3.0) ; (sys_platform == "darwin" or extra == "cpu") and extra == 'cpu'
Requires-Dist: dgl (>=2.2.1) ; (sys_platform == "darwin" or extra == "cpu") and extra == 'cpu'
Requires-Dist: deeprobust (>=0.2.10) ; (sys_platform == "darwin" or extra == "cpu") and extra == 'cpu'
Provides-Extra: cuda118
Requires-Dist: torch (>=2.3.0) ; (sys_platform == "darwin" and extra == "cuda") and extra == 'cuda118'
Requires-Dist: dgl-cu111 (>=0.6.1) ; (sys_platform == "darwin" and extra == "cuda") and extra == 'cuda118'
Requires-Dist: deeprobust (>=0.2.10) ; (sys_platform == "darwin" and extra == "cuda") and extra == 'cuda118'
